var2pharm/__init__.py
var2pharm/__main__.py
var2pharm/bam2gdf.py
var2pharm/bam2report.py
var2pharm/bam2sdf.py
var2pharm/common.py
var2pharm/report.py
var2pharm/sdf2gdf.py
var2pharm/sglib.py
var2pharm/version.py
var2pharm/resources/__init__.py
var2pharm/resources/cpic/__init__.py
var2pharm/resources/cpic/cpicPairs.csv
var2pharm/resources/pgkb/__init__.py
var2pharm/resources/pgkb/actions.txt
var2pharm/resources/r/__init__.py
var2pharm/resources/r/cpa.R
var2pharm/resources/r/plotcov.R
var2pharm/resources/sg/__init__.py
var2pharm/resources/sg/gene_table.txt
var2pharm/resources/sg/phenotype_table.txt
var2pharm/resources/sg/snp_table.txt
var2pharm/resources/sg/star_table.txt
var2pharm-0.0.4.dist-info/LICENSE
var2pharm-0.0.4.dist-info/METADATA
var2pharm-0.0.4.dist-info/WHEEL
var2pharm-0.0.4.dist-info/entry_points.txt
var2pharm-0.0.4.dist-info/top_level.txt
var2pharm-0.0.4.dist-info/RECORD
